{
  "version": "7",
  "dialect": "mysql",
  "entries": [
    {
      "idx": 0,
      "version": "5",
      "when": 1777206315974,
      "tag": "0000_init",
      "breakpoints": true
    },
    {
      "idx": 1,
      "version": "5",
      "when": 1779571200000,
      "tag": "0001_add_dominant_color_category",
      "breakpoints": true
    },
    {
      "idx": 2,
      "version": "5",
      "when": 1779638400000,
      "tag": "0002_add_category_index",
      "breakpoints": true
    },
    {
      "idx": 3,
      "version": "5",
      "when": 1779724800000,
      "tag": "0003_unify_gender",
      "breakpoints": true
    },
    {
      "idx": 4,
      "version": "5",
      "when": 1779811200000,
      "tag": "0004_reset_dominant_color_for_rederive",
      "breakpoints": true
    },
    {
      "idx": 5,
      "version": "5",
      "when": 1779897600000,
      "tag": "0005_add_rarity_columns",
      "breakpoints": true
    },
    {
      "idx": 6,
      "version": "5",
      "when": 1779984000000,
      "tag": "0006_genesis_cat_to_sub1",
      "breakpoints": true
    },
    {
      "idx": 7,
      "version": "5",
      "when": 1780070400000,
      "tag": "0007_reset_yellow_for_rederive",
      "breakpoints": true
    },
    {
      "idx": 8,
      "version": "5",
      "when": 1780243200000,
      "tag": "0008_reset_color_for_yellow_window",
      "breakpoints": true
    },
    {
      "idx": 9,
      "version": "5",
      "when": 1784419200000,
      "tag": "0009_add_listings_table",
      "breakpoints": true
    },
    {
      "idx": 10,
      "version": "5",
      "when": 1784505600000,
      "tag": "0010_signed_at_bigint",
      "breakpoints": true
    },
    {
      "idx": 11,
      "version": "5",
      "when": 1784505700000,
      "tag": "0011_add_listings_network",
      "breakpoints": true
    },
    {
      "idx": 12,
      "version": "5",
      "when": 1784678400000,
      "tag": "0012_listings_v3_cats_bundle",
      "breakpoints": true
    },
    {
      "idx": 13,
      "version": "5",
      "when": 1784678500000,
      "tag": "0013_add_bids_table",
      "breakpoints": true
    }
  ]
}
